{
  "flight_id": "BAW117_2026-04-10",
  "metadata": {
    "callsign": "BAW117",
    "iata": "BA117",
    "airline_icao": "BAW",
    "aircraft_type": "Boeing 777-300ER",
    "origin": "JFK",
    "destination": "LHR",
    "departure_utc": "2026-04-10T22:15:00Z",
    "duration_seconds": 24600,
    "data_sources": {
      "adsb": { "source": "OpenSky Network REST API v1.3", "retrieved_utc": "2026-04-12T10:00:00Z" },
      "weather": { "source": "ECMWF ERA5 reanalysis via CDS API v0.7.7", "retrieved_utc": "2026-04-13T08:00:00Z" },
      "aircraft_performance": { "source": "pycontrails PSFlight (ICAO EDB v31)", "retrieved_utc": "2026-04-13T08:00:00Z" },
      "cocip": { "source": "pycontrails CoCiP v0.61.0", "retrieved_utc": "2026-04-13T09:00:00Z" }
    }
  },
  "track_actual": [
    {"t":"2026-04-10T22:15:00Z","lat":40.6413,"lon":-73.7781,"alt_ft":0,"tas_ms":0,"fuel_burn_kg_s":0,"in_issr":false,"segment_forcing_j_m":0},
    {"t":"2026-04-10T22:25:00Z","lat":40.72,"lon":-73.65,"alt_ft":8000,"tas_ms":120,"fuel_burn_kg_s":2.8,"in_issr":false,"segment_forcing_j_m":0},
    {"t":"2026-04-10T22:35:00Z","lat":40.85,"lon":-73.40,"alt_ft":18000,"tas_ms":180,"fuel_burn_kg_s":2.5,"in_issr":false,"segment_forcing_j_m":0},
    {"t":"2026-04-10T22:50:00Z","lat":41.10,"lon":-72.90,"alt_ft":32000,"tas_ms":228,"fuel_burn_kg_s":2.1,"in_issr":false,"segment_forcing_j_m":0},
    {"t":"2026-04-10T23:00:00Z","lat":41.35,"lon":-72.40,"alt_ft":35000,"tas_ms":232,"fuel_burn_kg_s":2.0,"in_issr":false,"segment_forcing_j_m":0},
    {"t":"2026-04-10T23:15:00Z","lat":41.80,"lon":-71.50,"alt_ft":36000,"tas_ms":235,"fuel_burn_kg_s":1.95,"in_issr":false,"segment_forcing_j_m":0},
    {"t":"2026-04-10T23:30:00Z","lat":42.30,"lon":-70.50,"alt_ft":37000,"tas_ms":238,"fuel_burn_kg_s":1.90,"in_issr":false,"segment_forcing_j_m":0},
    {"t":"2026-04-10T23:45:00Z","lat":42.85,"lon":-69.30,"alt_ft":37000,"tas_ms":240,"fuel_burn_kg_s":1.88,"in_issr":false,"segment_forcing_j_m":0.2},
    {"t":"2026-04-11T00:00:00Z","lat":43.40,"lon":-68.00,"alt_ft":37000,"tas_ms":241,"fuel_burn_kg_s":1.87,"in_issr":false,"segment_forcing_j_m":0.1},
    {"t":"2026-04-11T00:15:00Z","lat":44.00,"lon":-66.50,"alt_ft":37000,"tas_ms":242,"fuel_burn_kg_s":1.86,"in_issr":true,"segment_forcing_j_m":4.8},
    {"t":"2026-04-11T00:30:00Z","lat":44.60,"lon":-64.80,"alt_ft":37000,"tas_ms":243,"fuel_burn_kg_s":1.85,"in_issr":true,"segment_forcing_j_m":6.2},
    {"t":"2026-04-11T00:45:00Z","lat":45.20,"lon":-63.00,"alt_ft":37000,"tas_ms":244,"fuel_burn_kg_s":1.84,"in_issr":true,"segment_forcing_j_m":7.1},
    {"t":"2026-04-11T01:00:00Z","lat":45.85,"lon":-61.00,"alt_ft":37000,"tas_ms":244,"fuel_burn_kg_s":1.83,"in_issr":true,"segment_forcing_j_m":8.3},
    {"t":"2026-04-11T01:15:00Z","lat":46.50,"lon":-58.80,"alt_ft":37000,"tas_ms":245,"fuel_burn_kg_s":1.82,"in_issr":true,"segment_forcing_j_m":9.0},
    {"t":"2026-04-11T01:30:00Z","lat":47.15,"lon":-56.50,"alt_ft":37000,"tas_ms":245,"fuel_burn_kg_s":1.82,"in_issr":true,"segment_forcing_j_m":9.8},
    {"t":"2026-04-11T01:45:00Z","lat":47.80,"lon":-54.00,"alt_ft":37000,"tas_ms":246,"fuel_burn_kg_s":1.81,"in_issr":true,"segment_forcing_j_m":10.2},
    {"t":"2026-04-11T02:00:00Z","lat":48.40,"lon":-51.50,"alt_ft":37000,"tas_ms":246,"fuel_burn_kg_s":1.80,"in_issr":true,"segment_forcing_j_m":9.5},
    {"t":"2026-04-11T02:15:00Z","lat":49.00,"lon":-48.80,"alt_ft":37000,"tas_ms":247,"fuel_burn_kg_s":1.79,"in_issr":true,"segment_forcing_j_m":8.7},
    {"t":"2026-04-11T02:30:00Z","lat":49.55,"lon":-46.00,"alt_ft":37000,"tas_ms":247,"fuel_burn_kg_s":1.78,"in_issr":true,"segment_forcing_j_m":7.9},
    {"t":"2026-04-11T02:45:00Z","lat":50.10,"lon":-43.00,"alt_ft":37000,"tas_ms":248,"fuel_burn_kg_s":1.77,"in_issr":true,"segment_forcing_j_m":6.5},
    {"t":"2026-04-11T03:00:00Z","lat":50.60,"lon":-40.00,"alt_ft":37000,"tas_ms":248,"fuel_burn_kg_s":1.76,"in_issr":true,"segment_forcing_j_m":5.8},
    {"t":"2026-04-11T03:15:00Z","lat":51.05,"lon":-37.00,"alt_ft":37000,"tas_ms":248,"fuel_burn_kg_s":1.75,"in_issr":true,"segment_forcing_j_m":4.2},
    {"t":"2026-04-11T03:30:00Z","lat":51.45,"lon":-34.00,"alt_ft":37000,"tas_ms":249,"fuel_burn_kg_s":1.74,"in_issr":false,"segment_forcing_j_m":0.3},
    {"t":"2026-04-11T03:45:00Z","lat":51.80,"lon":-31.00,"alt_ft":37000,"tas_ms":249,"fuel_burn_kg_s":1.73,"in_issr":false,"segment_forcing_j_m":0.1},
    {"t":"2026-04-11T04:00:00Z","lat":52.10,"lon":-28.00,"alt_ft":37000,"tas_ms":249,"fuel_burn_kg_s":1.72,"in_issr":true,"segment_forcing_j_m":5.1},
    {"t":"2026-04-11T04:15:00Z","lat":52.35,"lon":-25.00,"alt_ft":37000,"tas_ms":250,"fuel_burn_kg_s":1.71,"in_issr":true,"segment_forcing_j_m":6.8},
    {"t":"2026-04-11T04:30:00Z","lat":52.55,"lon":-22.00,"alt_ft":37000,"tas_ms":250,"fuel_burn_kg_s":1.70,"in_issr":true,"segment_forcing_j_m":7.4},
    {"t":"2026-04-11T04:45:00Z","lat":52.70,"lon":-19.00,"alt_ft":37000,"tas_ms":250,"fuel_burn_kg_s":1.69,"in_issr":true,"segment_forcing_j_m":6.0},
    {"t":"2026-04-11T05:00:00Z","lat":52.80,"lon":-16.00,"alt_ft":37000,"tas_ms":249,"fuel_burn_kg_s":1.68,"in_issr":true,"segment_forcing_j_m":4.8},
    {"t":"2026-04-11T05:15:00Z","lat":52.85,"lon":-13.00,"alt_ft":36000,"tas_ms":248,"fuel_burn_kg_s":1.72,"in_issr":false,"segment_forcing_j_m":0.2},
    {"t":"2026-04-11T05:30:00Z","lat":52.80,"lon":-10.00,"alt_ft":35000,"tas_ms":245,"fuel_burn_kg_s":1.78,"in_issr":false,"segment_forcing_j_m":0},
    {"t":"2026-04-11T05:45:00Z","lat":52.50,"lon":-7.50,"alt_ft":32000,"tas_ms":238,"fuel_burn_kg_s":1.85,"in_issr":false,"segment_forcing_j_m":0},
    {"t":"2026-04-11T06:00:00Z","lat":52.10,"lon":-5.20,"alt_ft":25000,"tas_ms":210,"fuel_burn_kg_s":2.0,"in_issr":false,"segment_forcing_j_m":0},
    {"t":"2026-04-11T06:15:00Z","lat":51.80,"lon":-3.00,"alt_ft":15000,"tas_ms":170,"fuel_burn_kg_s":2.2,"in_issr":false,"segment_forcing_j_m":0},
    {"t":"2026-04-11T06:25:00Z","lat":51.55,"lon":-1.20,"alt_ft":5000,"tas_ms":100,"fuel_burn_kg_s":2.5,"in_issr":false,"segment_forcing_j_m":0},
    {"t":"2026-04-11T05:05:00Z","lat":51.47,"lon":-0.4614,"alt_ft":0,"tas_ms":0,"fuel_burn_kg_s":0,"in_issr":false,"segment_forcing_j_m":0}
  ],
  "track_counterfactual": [
    {"t":"2026-04-10T22:15:00Z","lat":40.6413,"lon":-73.7781,"alt_ft":0,"tas_ms":0,"fuel_burn_kg_s":0,"in_issr":false,"segment_forcing_j_m":0},
    {"t":"2026-04-10T22:25:00Z","lat":40.72,"lon":-73.65,"alt_ft":8000,"tas_ms":120,"fuel_burn_kg_s":2.8,"in_issr":false,"segment_forcing_j_m":0},
    {"t":"2026-04-10T22:35:00Z","lat":40.85,"lon":-73.40,"alt_ft":18000,"tas_ms":180,"fuel_burn_kg_s":2.5,"in_issr":false,"segment_forcing_j_m":0},
    {"t":"2026-04-10T22:50:00Z","lat":41.10,"lon":-72.90,"alt_ft":32000,"tas_ms":228,"fuel_burn_kg_s":2.15,"in_issr":false,"segment_forcing_j_m":0},
    {"t":"2026-04-10T23:00:00Z","lat":41.35,"lon":-72.40,"alt_ft":33000,"tas_ms":230,"fuel_burn_kg_s":2.05,"in_issr":false,"segment_forcing_j_m":0},
    {"t":"2026-04-10T23:15:00Z","lat":41.80,"lon":-71.50,"alt_ft":33000,"tas_ms":233,"fuel_burn_kg_s":2.00,"in_issr":false,"segment_forcing_j_m":0},
    {"t":"2026-04-10T23:30:00Z","lat":42.30,"lon":-70.50,"alt_ft":33000,"tas_ms":235,"fuel_burn_kg_s":1.98,"in_issr":false,"segment_forcing_j_m":0},
    {"t":"2026-04-10T23:45:00Z","lat":42.85,"lon":-69.30,"alt_ft":33000,"tas_ms":237,"fuel_burn_kg_s":1.96,"in_issr":false,"segment_forcing_j_m":0},
    {"t":"2026-04-11T00:00:00Z","lat":43.40,"lon":-68.00,"alt_ft":33000,"tas_ms":238,"fuel_burn_kg_s":1.95,"in_issr":false,"segment_forcing_j_m":0},
    {"t":"2026-04-11T00:15:00Z","lat":44.00,"lon":-66.50,"alt_ft":33000,"tas_ms":239,"fuel_burn_kg_s":1.94,"in_issr":false,"segment_forcing_j_m":0.3},
    {"t":"2026-04-11T00:30:00Z","lat":44.60,"lon":-64.80,"alt_ft":33000,"tas_ms":240,"fuel_burn_kg_s":1.93,"in_issr":false,"segment_forcing_j_m":0.2},
    {"t":"2026-04-11T00:45:00Z","lat":45.20,"lon":-63.00,"alt_ft":33000,"tas_ms":240,"fuel_burn_kg_s":1.93,"in_issr":false,"segment_forcing_j_m":0.1},
    {"t":"2026-04-11T01:00:00Z","lat":45.85,"lon":-61.00,"alt_ft":33000,"tas_ms":241,"fuel_burn_kg_s":1.92,"in_issr":false,"segment_forcing_j_m":0},
    {"t":"2026-04-11T01:15:00Z","lat":46.50,"lon":-58.80,"alt_ft":33000,"tas_ms":241,"fuel_burn_kg_s":1.92,"in_issr":false,"segment_forcing_j_m":0},
    {"t":"2026-04-11T01:30:00Z","lat":47.15,"lon":-56.50,"alt_ft":33000,"tas_ms":242,"fuel_burn_kg_s":1.91,"in_issr":false,"segment_forcing_j_m":0},
    {"t":"2026-04-11T01:45:00Z","lat":47.80,"lon":-54.00,"alt_ft":33000,"tas_ms":242,"fuel_burn_kg_s":1.91,"in_issr":false,"segment_forcing_j_m":0.1},
    {"t":"2026-04-11T02:00:00Z","lat":48.40,"lon":-51.50,"alt_ft":33000,"tas_ms":243,"fuel_burn_kg_s":1.90,"in_issr":false,"segment_forcing_j_m":0},
    {"t":"2026-04-11T02:15:00Z","lat":49.00,"lon":-48.80,"alt_ft":33000,"tas_ms":243,"fuel_burn_kg_s":1.90,"in_issr":false,"segment_forcing_j_m":0},
    {"t":"2026-04-11T02:30:00Z","lat":49.55,"lon":-46.00,"alt_ft":33000,"tas_ms":244,"fuel_burn_kg_s":1.89,"in_issr":false,"segment_forcing_j_m":0},
    {"t":"2026-04-11T02:45:00Z","lat":50.10,"lon":-43.00,"alt_ft":33000,"tas_ms":244,"fuel_burn_kg_s":1.89,"in_issr":false,"segment_forcing_j_m":0},
    {"t":"2026-04-11T03:00:00Z","lat":50.60,"lon":-40.00,"alt_ft":33000,"tas_ms":244,"fuel_burn_kg_s":1.88,"in_issr":false,"segment_forcing_j_m":0},
    {"t":"2026-04-11T03:15:00Z","lat":51.05,"lon":-37.00,"alt_ft":33000,"tas_ms":245,"fuel_burn_kg_s":1.88,"in_issr":false,"segment_forcing_j_m":0},
    {"t":"2026-04-11T03:30:00Z","lat":51.45,"lon":-34.00,"alt_ft":35000,"tas_ms":247,"fuel_burn_kg_s":1.80,"in_issr":false,"segment_forcing_j_m":0},
    {"t":"2026-04-11T03:45:00Z","lat":51.80,"lon":-31.00,"alt_ft":37000,"tas_ms":249,"fuel_burn_kg_s":1.73,"in_issr":false,"segment_forcing_j_m":0},
    {"t":"2026-04-11T04:00:00Z","lat":52.10,"lon":-28.00,"alt_ft":33000,"tas_ms":244,"fuel_burn_kg_s":1.89,"in_issr":false,"segment_forcing_j_m":0.4},
    {"t":"2026-04-11T04:15:00Z","lat":52.35,"lon":-25.00,"alt_ft":33000,"tas_ms":245,"fuel_burn_kg_s":1.88,"in_issr":false,"segment_forcing_j_m":0.2},
    {"t":"2026-04-11T04:30:00Z","lat":52.55,"lon":-22.00,"alt_ft":33000,"tas_ms":245,"fuel_burn_kg_s":1.88,"in_issr":false,"segment_forcing_j_m":0.1},
    {"t":"2026-04-11T04:45:00Z","lat":52.70,"lon":-19.00,"alt_ft":33000,"tas_ms":245,"fuel_burn_kg_s":1.87,"in_issr":false,"segment_forcing_j_m":0},
    {"t":"2026-04-11T05:00:00Z","lat":52.80,"lon":-16.00,"alt_ft":33000,"tas_ms":244,"fuel_burn_kg_s":1.87,"in_issr":false,"segment_forcing_j_m":0},
    {"t":"2026-04-11T05:15:00Z","lat":52.85,"lon":-13.00,"alt_ft":34000,"tas_ms":246,"fuel_burn_kg_s":1.82,"in_issr":false,"segment_forcing_j_m":0},
    {"t":"2026-04-11T05:30:00Z","lat":52.80,"lon":-10.00,"alt_ft":35000,"tas_ms":245,"fuel_burn_kg_s":1.78,"in_issr":false,"segment_forcing_j_m":0},
    {"t":"2026-04-11T05:45:00Z","lat":52.50,"lon":-7.50,"alt_ft":32000,"tas_ms":238,"fuel_burn_kg_s":1.85,"in_issr":false,"segment_forcing_j_m":0},
    {"t":"2026-04-11T06:00:00Z","lat":52.10,"lon":-5.20,"alt_ft":25000,"tas_ms":210,"fuel_burn_kg_s":2.0,"in_issr":false,"segment_forcing_j_m":0},
    {"t":"2026-04-11T06:15:00Z","lat":51.80,"lon":-3.00,"alt_ft":15000,"tas_ms":170,"fuel_burn_kg_s":2.2,"in_issr":false,"segment_forcing_j_m":0},
    {"t":"2026-04-11T06:25:00Z","lat":51.55,"lon":-1.20,"alt_ft":5000,"tas_ms":100,"fuel_burn_kg_s":2.5,"in_issr":false,"segment_forcing_j_m":0},
    {"t":"2026-04-11T05:05:00Z","lat":51.47,"lon":-0.4614,"alt_ft":0,"tas_ms":0,"fuel_burn_kg_s":0,"in_issr":false,"segment_forcing_j_m":0}
  ],
  "issr_geojson_path": "/data/BAW117_2026-04-10_issr.geojson",
  "totals": {
    "actual": {
      "co2_fuel_kg": {"value": 189.4, "ci_low": 183.2, "ci_high": 195.6, "method": "PSFlight fuel model, EI_CO2=3.159", "source": "pycontrails v0.61.0 PSFlight + JetA constants"},
      "contrail_forcing_tco2e": {"value": 212.8, "ci_low": 63.8, "ci_high": 361.8, "method": "CoCiP energy forcing → GWP100 conversion", "source": "pycontrails CoCiP v0.61.0, Lee et al. 2021 ERF/RF ratio"},
      "non_co2_other_tco2e": {"value": 32.6, "ci_low": 12.4, "ci_high": 52.8, "method": "Lee et al. 2021 non-CO2 ERF factors (NOx, H2O, soot, sulfate)", "source": "Lee et al. 2021 (DOI: 10.1016/j.atmosenv.2020.117834)"},
      "total_warming_tco2e": {"value": 434.8, "ci_low": 259.4, "ci_high": 610.2, "method": "Sum of CO2 + contrail + non-CO2", "source": "Computed from component values"}
    },
    "counterfactual": {
      "co2_fuel_kg": {"value": 195.1, "ci_low": 188.7, "ci_high": 201.5, "method": "PSFlight fuel model at diverted altitudes", "source": "pycontrails v0.61.0 PSFlight"},
      "contrail_forcing_tco2e": {"value": 18.3, "ci_low": 5.5, "ci_high": 31.1, "method": "CoCiP at counterfactual altitudes", "source": "pycontrails CoCiP v0.61.0"},
      "non_co2_other_tco2e": {"value": 33.8, "ci_low": 12.9, "ci_high": 54.7, "method": "Lee et al. 2021 factors at higher fuel burn", "source": "Lee et al. 2021"},
      "total_warming_tco2e": {"value": 247.2, "ci_low": 207.1, "ci_high": 287.3, "method": "Sum at counterfactual altitudes", "source": "Computed"}
    },
    "avoidable_warming_tco2e": {"value": 187.6, "ci_low": 52.3, "ci_high": 322.9, "method": "Actual total − counterfactual total", "source": "Computed difference"},
    "fuel_penalty_kg": 5.7,
    "fuel_penalty_pct": 3.01
  },
  "counterfactual_spec": {
    "method": "Grid search across altitude offsets at each cruise segment, minimizing total energy forcing under fuel constraint. pycontrails CoCiP v0.61.0, PSFlight performance model.",
    "offsets_evaluated_ft": [-4000, -2000, 0, 2000, 4000],
    "fuel_constraint": "≤5% additional fuel burn over baseline",
    "selected_offset_ft_by_segment": [0, 0, 0, 0, 0, 0, 0, 0, -4000, -4000, -4000, -4000, -4000, -4000, -4000, -4000, -4000, -4000, -4000, -4000, -4000, -4000, 0, 0, -4000, -4000, -4000, -4000, -4000, 0, 0, 0, 0, 0, 0, 0]
  },
  "airline_context": {
    "carrier_name": "British Airways",
    "rank": 3,
    "total_carriers": 5,
    "flights_analyzed": 47,
    "leaderboard": [
      {"carrier": "Delta Air Lines", "avoidable_tco2e_per_flight": {"value": 95.2, "ci_low": 28.6, "ci_high": 161.8, "method": "Mean avoidable warming across analyzed flights", "source": "Pipeline aggregate"}},
      {"carrier": "Air France", "avoidable_tco2e_per_flight": {"value": 112.7, "ci_low": 33.8, "ci_high": 191.6, "method": "Mean avoidable warming across analyzed flights", "source": "Pipeline aggregate"}},
      {"carrier": "British Airways", "avoidable_tco2e_per_flight": {"value": 138.4, "ci_low": 41.5, "ci_high": 235.3, "method": "Mean avoidable warming across analyzed flights", "source": "Pipeline aggregate"}},
      {"carrier": "United Airlines", "avoidable_tco2e_per_flight": {"value": 156.9, "ci_low": 47.1, "ci_high": 266.7, "method": "Mean avoidable warming across analyzed flights", "source": "Pipeline aggregate"}},
      {"carrier": "American Airlines", "avoidable_tco2e_per_flight": {"value": 178.3, "ci_low": 53.5, "ci_high": 303.1, "method": "Mean avoidable warming across analyzed flights", "source": "Pipeline aggregate"}}
    ]
  },
  "assumptions": [
    {"field": "EI_CO2", "value": 3.159, "source": "pycontrails v0.61.0 JetA fuel model", "url": "https://py.contrails.org/api/pycontrails.core.fuel.html"},
    {"field": "GWP100_contrails", "value": "Applied via Lee et al. 2021 ERF factors", "source": "Lee et al. 2021", "url": "https://doi.org/10.1016/j.atmosenv.2020.117834"},
    {"field": "humidity_scaling", "value": "ConstantHumidityScaling(rhi_adj=0.99)", "source": "pycontrails CoCiP default for ERA5", "url": "https://py.contrails.org/"},
    {"field": "aircraft_performance", "value": "PSFlight (ICAO EDB v31)", "source": "pycontrails PSFlight", "url": "https://py.contrails.org/"},
    {"field": "EPA_car_factor", "value": "4.6 metric tons CO2/car/year", "source": "EPA Greenhouse Gas Equivalencies Calculator", "url": "https://www.epa.gov/energy/greenhouse-gas-equivalencies-calculator"}
  ],
  "data_gaps": [
    "Aircraft weight estimated from average load factor (0.835 IATA global); actual passenger count unknown.",
    "OpenSky barometric altitude used; geometric altitude may differ by up to 200 ft at cruise.",
    "ERA5 reanalysis humidity has known dry bias at upper troposphere; addressed via rhi_adj=0.99 scaling."
  ]
}
